my_package/__init__.py
my_package/main.py
my_package/data/Webjeux_games_names.txt
my_package/data/flipline_studio.png
webjeux_flash_downloader-1.5.dist-info/licenses/LICENSE
webjeux_flash_downloader-1.5.dist-info/METADATA
webjeux_flash_downloader-1.5.dist-info/WHEEL
webjeux_flash_downloader-1.5.dist-info/entry_points.txt
webjeux_flash_downloader-1.5.dist-info/top_level.txt
webjeux_flash_downloader-1.5.dist-info/RECORD
